digit_interface/__init__.py
digit_interface/digit.py
digit_interface/digit_handler.py
digit_interface-0.1.2.dist-info/LICENSE
digit_interface-0.1.2.dist-info/METADATA
digit_interface-0.1.2.dist-info/WHEEL
digit_interface-0.1.2.dist-info/top_level.txt
digit_interface-0.1.2.dist-info/zip-safe
digit_interface-0.1.2.dist-info/RECORD
