Metadata-Version: 2.1
Name: digit-interface
Version: 0.1.2
Summary: Interface for the DIGIT tactile sensor.
Home-page: https://github.com/facebookresearch/digit-interface
Author: Mike Lambeta, Roberto Calandra
Author-email: lambetam@fb.com, rcalandra@fb.com
License: LICENSE
Keywords: science
Platform: UNKNOWN
Classifier: Programming Language :: Python :: 3
Classifier: Operating System :: POSIX :: Linux
Requires-Python: >=3.6
Requires-Dist: numpy (>=1.16)
Requires-Dist: opencv-python
Requires-Dist: pyudev
